is_number_prime/__init__.py
is_number_prime/is_prime.py
is_number_prime-0.1.0.dist-info/METADATA
is_number_prime-0.1.0.dist-info/WHEEL
is_number_prime-0.1.0.dist-info/licenses/LICENSE
is_number_prime-0.1.0.dist-info/RECORD
