Metadata-Version: 2.4
Name: is_number_prime
Version: 0.1.0
Summary: Simple package for returning number is prime or not
Author-email: Your Name <your.email@example.com>
License: MIT
License-File: LICENSE
Requires-Python: >=3.6
